<?xml version="1.0"?>

<!-- Sea Hawk model config file -->
<!-- Lee Elliott 2002/12/26 leee-fgfs@spatial.freeserve.co.uk -->

<PropertyList>
 <path>SeaHawkpair.3ds</path>
 <offsets>
   <z-m>0.0</z-m>
   <pitch-deg>0</pitch-deg>
 </offsets>

<!-- Wing man -->
<!-- displacement offset -->
 <animation>
  <type>rotate</type>
  <object-name>CHull</object-name>
  <object-name>CFCanopy</object-name>
  <object-name>CCanopy</object-name>
  <object-name>CBCanopy</object-name>
  <object-name>CRudder</object-name>
  <object-name>CLElevator</object-name>
  <object-name>CRElevator</object-name>
  <object-name>CAHook</object-name>
  <object-name>CFStrut</object-name>
  <object-name>CFTyre</object-name>
  <object-name>CFDoor</object-name>
  <object-name>CBDoor</object-name>
  <object-name>CLDoor1</object-name>
  <object-name>CLDoor2</object-name>
  <object-name>CLStrut</object-name>
  <object-name>CLTyre</object-name>
  <object-name>CRStrut</object-name>
  <object-name>CRTyre</object-name>
  <object-name>CRDoor1</object-name>
  <object-name>CRDoor2</object-name>
  <object-name>CLAileron</object-name>
  <object-name>CRAileron</object-name>
  <object-name>CLFlap</object-name>
  <object-name>CRFlap</object-name>
  <object-name>CLWing</object-name>
  <object-name>CRWing</object-name>
  <property>/wingman/position-norm</property>
  <offset-deg>-90</offset-deg>
  <factor>90</factor>
  <center>
   <x-m>12.0</x-m>
   <y-m>0.0</y-m>
   <z-m>0.0</z-m>
  </center>
  <axis>
   <x>0</x>
   <y>0</y>
   <z>1</z>
  </axis>
 </animation>

 <animation>
  <type>rotate</type>
  <object-name>CHull</object-name>
  <object-name>CFCanopy</object-name>
  <object-name>CCanopy</object-name>
  <object-name>CBCanopy</object-name>
  <object-name>CRudder</object-name>
  <object-name>CLElevator</object-name>
  <object-name>CRElevator</object-name>
  <object-name>CAHook</object-name>
  <object-name>CFStrut</object-name>
  <object-name>CFTyre</object-name>
  <object-name>CFDoor</object-name>
  <object-name>CBDoor</object-name>
  <object-name>CLDoor1</object-name>
  <object-name>CLDoor2</object-name>
  <object-name>CLStrut</object-name>
  <object-name>CLTyre</object-name>
  <object-name>CRStrut</object-name>
  <object-name>CRTyre</object-name>
  <object-name>CRDoor1</object-name>
  <object-name>CRDoor2</object-name>
  <object-name>CLAileron</object-name>
  <object-name>CRAileron</object-name>
  <object-name>CLFlap</object-name>
  <object-name>CRFlap</object-name>
  <object-name>CLWing</object-name>
  <object-name>CRWing</object-name>
  <property>/wingman/position-norm</property>
  <offset-deg>90</offset-deg>
  <factor>-90</factor>
  <center>
   <x-m>0.0</x-m>
   <y-m>0.0</y-m>
   <z-m>0.0</z-m>
  </center>
  <axis>
   <x>0</x>
   <y>0</y>
   <z>1</z>
  </axis>
 </animation>

<!-- pitch offset -->
 <animation>
  <type>rotate</type>
  <object-name>CHull</object-name>
  <object-name>CFCanopy</object-name>
  <object-name>CCanopy</object-name>
  <object-name>CBCanopy</object-name>
  <object-name>CRudder</object-name>
  <object-name>CLElevator</object-name>
  <object-name>CRElevator</object-name>
  <object-name>CAHook</object-name>
  <object-name>CFStrut</object-name>
  <object-name>CFTyre</object-name>
  <object-name>CFDoor</object-name>
  <object-name>CBDoor</object-name>
  <object-name>CLDoor1</object-name>
  <object-name>CLDoor2</object-name>
  <object-name>CLStrut</object-name>
  <object-name>CLTyre</object-name>
  <object-name>CRStrut</object-name>
  <object-name>CRTyre</object-name>
  <object-name>CRDoor1</object-name>
  <object-name>CRDoor2</object-name>
  <object-name>CLAileron</object-name>
  <object-name>CRAileron</object-name>
  <object-name>CLFlap</object-name>
  <object-name>CRFlap</object-name>
  <object-name>CLWing</object-name>
  <object-name>CRWing</object-name>
  <property>/orientation/pitch-deg</property>
  <factor>1.0</factor>
  <center>
   <x-m>12.0</x-m>
   <y-m>12.0</y-m>
   <z-m>0.0</z-m>
  </center>
  <axis>
   <x>0</x>
   <y>1</y>
   <z>0</z>
  </axis>
 </animation>

 <animation>
  <type>rotate</type>
  <object-name>CHull</object-name>
  <object-name>CFCanopy</object-name>
  <object-name>CCanopy</object-name>
  <object-name>CBCanopy</object-name>
  <object-name>CRudder</object-name>
  <object-name>CLElevator</object-name>
  <object-name>CRElevator</object-name>
  <object-name>CAHook</object-name>
  <object-name>CFStrut</object-name>
  <object-name>CFTyre</object-name>
  <object-name>CFDoor</object-name>
  <object-name>CBDoor</object-name>
  <object-name>CLDoor1</object-name>
  <object-name>CLDoor2</object-name>
  <object-name>CLStrut</object-name>
  <object-name>CLTyre</object-name>
  <object-name>CRStrut</object-name>
  <object-name>CRTyre</object-name>
  <object-name>CRDoor1</object-name>
  <object-name>CRDoor2</object-name>
  <object-name>CLAileron</object-name>
  <object-name>CRAileron</object-name>
  <object-name>CLFlap</object-name>
  <object-name>CRFlap</object-name>
  <object-name>CLWing</object-name>
  <object-name>CRWing</object-name>
  <property>/orientation/pitch-deg</property>
  <factor>-1</factor>
  <center>
   <x-m>0.0</x-m>
   <y-m>0.0</y-m>
   <z-m>0.0</z-m>
  </center>
  <axis>
   <x>0</x>
   <y>1</y>
   <z>0</z>
  </axis>
 </animation>

<!-- roll offset -->
 <animation>
  <type>rotate</type>
  <object-name>CHull</object-name>
  <object-name>CFCanopy</object-name>
  <object-name>CCanopy</object-name>
  <object-name>CBCanopy</object-name>
  <object-name>CRudder</object-name>
  <object-name>CLElevator</object-name>
  <object-name>CRElevator</object-name>
  <object-name>CAHook</object-name>
  <object-name>CFStrut</object-name>
  <object-name>CFTyre</object-name>
  <object-name>CFDoor</object-name>
  <object-name>CBDoor</object-name>
  <object-name>CLDoor1</object-name>
  <object-name>CLDoor2</object-name>
  <object-name>CLStrut</object-name>
  <object-name>CLTyre</object-name>
  <object-name>CRStrut</object-name>
  <object-name>CRTyre</object-name>
  <object-name>CRDoor1</object-name>
  <object-name>CRDoor2</object-name>
  <object-name>CLAileron</object-name>
  <object-name>CRAileron</object-name>
  <object-name>CLFlap</object-name>
  <object-name>CRFlap</object-name>
  <object-name>CLWing</object-name>
  <object-name>CRWing</object-name>
  <property>/orientation/roll-deg</property>
  <factor>1.0</factor>
  <center>
   <x-m>12.0</x-m>
   <y-m>0.0</y-m>
   <z-m>0.0</z-m>
  </center>
  <axis>
   <x>0</x>
   <y>1</y>
   <z>0</z>
  </axis>
 </animation>

 <animation>
  <type>rotate</type>
  <object-name>CHull</object-name>
  <object-name>CFCanopy</object-name>
  <object-name>CCanopy</object-name>
  <object-name>CBCanopy</object-name>
  <object-name>CRudder</object-name>
  <object-name>CLElevator</object-name>
  <object-name>CRElevator</object-name>
  <object-name>CAHook</object-name>
  <object-name>CFStrut</object-name>
  <object-name>CFTyre</object-name>
  <object-name>CFDoor</object-name>
  <object-name>CBDoor</object-name>
  <object-name>CLDoor1</object-name>
  <object-name>CLDoor2</object-name>
  <object-name>CLStrut</object-name>
  <object-name>CLTyre</object-name>
  <object-name>CRStrut</object-name>
  <object-name>CRTyre</object-name>
  <object-name>CRDoor1</object-name>
  <object-name>CRDoor2</object-name>
  <object-name>CLAileron</object-name>
  <object-name>CRAileron</object-name>
  <object-name>CLFlap</object-name>
  <object-name>CRFlap</object-name>
  <object-name>CLWing</object-name>
  <object-name>CRWing</object-name>
  <property>/orientation/roll-deg</property>
  <factor>-1</factor>
  <center>
   <x-m>0.0</x-m>
   <y-m>0.0</y-m>
   <z-m>0.0</z-m>
  </center>
  <axis>
   <x>0</x>
   <y>1</y>
   <z>0</z>
  </axis>
 </animation>

<!-- heading offset -->
<!-- <animation>
  <type>rotate</type>
  <object-name>CHull</object-name>
  <object-name>CFCanopy</object-name>
  <object-name>CCanopy</object-name>
  <object-name>CBCanopy</object-name>
  <object-name>CRudder</object-name>
  <object-name>CLElevator</object-name>
  <object-name>CRElevator</object-name>
  <object-name>CAHook</object-name>
  <object-name>CFStrut</object-name>
  <object-name>CFTyre</object-name>
  <object-name>CFDoor</object-name>
  <object-name>CBDoor</object-name>
  <object-name>CLDoor1</object-name>
  <object-name>CLDoor2</object-name>
  <object-name>CLStrut</object-name>
  <object-name>CLTyre</object-name>
  <object-name>CRStrut</object-name>
  <object-name>CRTyre</object-name>
  <object-name>CRDoor1</object-name>
  <object-name>CRDoor2</object-name>
  <object-name>CLAileron</object-name>
  <object-name>CRAileron</object-name>
  <object-name>CLFlap</object-name>
  <object-name>CRFlap</object-name>
  <object-name>CLWing</object-name>
  <object-name>CRWing</object-name>
  <property>/orientation/heading-deg</property>
  <factor>1.0</factor>
  <center>
   <x-m>15.0</x-m>
   <y-m>15.0</y-m>
   <z-m>0.0</z-m>
  </center>
  <axis>
   <x>0</x>
   <y>1</y>
   <z>0</z>
  </axis>
 </animation>

 <animation>
  <type>rotate</type>
  <object-name>CHull</object-name>
  <object-name>CFCanopy</object-name>
  <object-name>CCanopy</object-name>
  <object-name>CBCanopy</object-name>
  <object-name>CRudder</object-name>
  <object-name>CLElevator</object-name>
  <object-name>CRElevator</object-name>
  <object-name>CAHook</object-name>
  <object-name>CFStrut</object-name>
  <object-name>CFTyre</object-name>
  <object-name>CFDoor</object-name>
  <object-name>CBDoor</object-name>
  <object-name>CLDoor1</object-name>
  <object-name>CLDoor2</object-name>
  <object-name>CLStrut</object-name>
  <object-name>CLTyre</object-name>
  <object-name>CRStrut</object-name>
  <object-name>CRTyre</object-name>
  <object-name>CRDoor1</object-name>
  <object-name>CRDoor2</object-name>
  <object-name>CLAileron</object-name>
  <object-name>CRAileron</object-name>
  <object-name>CLFlap</object-name>
  <object-name>CRFlap</object-name>
  <object-name>CLWing</object-name>
  <object-name>CRWing</object-name>
  <property>/orientation/heading-deg</property>
  <factor>-1</factor>
  <center>
   <x-m>0.0</x-m>
   <y-m>0.0</y-m>
   <z-m>0.0</z-m>
  </center>
  <axis>
   <x>0</x>
   <y>1</y>
   <z>0</z>
  </axis>
 </animation>
-->
<!-- Canopy -->
 <animation>
  <type>rotate</type>
  <object-name>Canopy</object-name>
  <property>/canopy/position-norm</property>
  <factor>4.0</factor>
  <center>
   <x-m>-2.0</x-m>
   <y-m>0.0</y-m>
   <z-m>-10.0</z-m>
  </center>
  <axis>
   <x>0</x>
   <y>1</y>
   <z>0</z>
  </axis>
 </animation>

 <animation>
  <type>rotate</type>
  <object-name>CCanopy</object-name>
  <property>/canopy/position-norm</property>
  <factor>4.0</factor>
  <center>
   <x-m>-2.0</x-m>
   <y-m>0.0</y-m>
   <z-m>-10.0</z-m>
  </center>
  <axis>
   <x>0</x>
   <y>1</y>
   <z>0</z>
  </axis>
 </animation>

<!-- Left Wing -->
 <animation>
  <type>rotate</type>
  <object-name>LWing</object-name>
  <object-name>LAileron</object-name>
  <object-name>LFlap</object-name>
  <property>/canopy/position-norm</property>
  <factor>-108</factor>
  <center>
   <x-m>0.0</x-m>
   <y-m>-1.66</y-m>
   <z-m>0.1</z-m>
  </center>
  <axis>
   <x>1</x>
   <y>0</y>
   <z>0</z>
  </axis>
 </animation>

 <animation>
  <type>rotate</type>
  <object-name>CLWing</object-name>
  <object-name>CLAileron</object-name>
  <object-name>CLFlap</object-name>
  <property>/canopy/position-norm</property>
  <factor>-108</factor>
  <center>
   <x-m>0.0</x-m>
   <y-m>-1.66</y-m>
   <z-m>0.1</z-m>
  </center>
  <axis>
   <x>1</x>
   <y>0</y>
   <z>0</z>
  </axis>
 </animation>

<!-- Right Wing -->
 <animation>
  <type>rotate</type>
  <object-name>RWing</object-name>
  <object-name>RAileron</object-name>
  <object-name>RFlap</object-name>
  <property>/canopy/position-norm</property>
  <factor>108</factor>
  <center>
   <x-m>0.0</x-m>
   <y-m>1.66</y-m>
   <z-m>0.1</z-m>
  </center>
  <axis>
   <x>1</x>
   <y>0</y>
   <z>0</z>
  </axis>
 </animation>

 <animation>
  <type>rotate</type>
  <object-name>CRWing</object-name>
  <object-name>CRAileron</object-name>
  <object-name>CRFlap</object-name>
  <property>/canopy/position-norm</property>
  <factor>108</factor>
  <center>
   <x-m>0.0</x-m>
   <y-m>1.66</y-m>
   <z-m>0.1</z-m>
  </center>
  <axis>
   <x>1</x>
   <y>0</y>
   <z>0</z>
  </axis>
 </animation>

<!-- Rudder bits -->
 <animation>
  <type>rotate</type>
  <object-name>Rudder</object-name>
  <property>/surface-positions/rudder-pos-norm</property>
  <factor>-50</factor>
  <center>
   <x-m>5.38</x-m>
   <y-m>0.0</y-m>
   <z-m>0.0</z-m>
  </center>
  <axis>
   <x>0.0</x>
   <y>0</y>
   <z>1</z>
  </axis>
 </animation>

 <animation>
  <type>rotate</type>
  <object-name>CRudder</object-name>
  <property>/surface-positions/rudder-pos-norm</property>
  <factor>-50</factor>
  <center>
   <x-m>5.38</x-m>
   <y-m>0.0</y-m>
   <z-m>0.0</z-m>
  </center>
  <axis>
   <x>0.0</x>
   <y>0</y>
   <z>1</z>
  </axis>
 </animation>

<!-- Elevator bits -->
 <animation>
  <type>rotate</type>
  <object-name>LElevator</object-name>
  <property>/surface-positions/elevator-pos-norm</property>
  <factor>40</factor>
  <center>
   <x-m>5.39</x-m>
   <y-m>0.0</y-m>
   <z-m>0.70</z-m>
  </center>
  <axis>
   <x>0</x>
   <y>1.0</y>
   <z>0.0</z>
  </axis>
 </animation>

 <animation>
  <type>rotate</type>
  <object-name>CLElevator</object-name>
  <property>/surface-positions/elevator-pos-norm</property>
  <factor>40</factor>
  <center>
   <x-m>5.39</x-m>
   <y-m>0.0</y-m>
   <z-m>0.70</z-m>
  </center>
  <axis>
   <x>0</x>
   <y>1.0</y>
   <z>0.0</z>
  </axis>
 </animation>

 <animation>
  <type>rotate</type>
  <object-name>RElevator</object-name>
  <property>/surface-positions/elevator-pos-norm</property>
  <factor>40</factor>
  <center>
   <x-m>5.39</x-m>
   <y-m>0.0</y-m>
   <z-m>0.70</z-m>
  </center>
  <axis>
   <x>0.0</x>
   <y>1.0</y>
   <z>0.0</z>
  </axis>
 </animation>

 <animation>
  <type>rotate</type>
  <object-name>CRElevator</object-name>
  <property>/surface-positions/elevator-pos-norm</property>
  <factor>40</factor>
  <center>
   <x-m>5.39</x-m>
   <y-m>0.0</y-m>
   <z-m>0.70</z-m>
  </center>
  <axis>
   <x>0.0</x>
   <y>1.0</y>
   <z>0.0</z>
  </axis>
 </animation>

<!-- Alieron bits -->
 <animation>
  <type>rotate</type>
  <object-name>LAileron</object-name>
  <property>/surface-positions/left-aileron-pos-norm</property>
  <factor>40</factor>
  <center>
   <x-m>0.24</x-m>
   <y-m>-3.39</y-m>
   <z-m>0.04</z-m>
  </center>
  <axis>
   <x>0.17</x>
   <y>1</y>
   <z>-0.065</z>
  </axis>
 </animation>

 <animation>
  <type>rotate</type>
  <object-name>CLAileron</object-name>
  <property>/surface-positions/left-aileron-pos-norm</property>
  <factor>40</factor>
  <center>
   <x-m>0.24</x-m>
   <y-m>-3.39</y-m>
   <z-m>0.04</z-m>
  </center>
  <axis>
   <x>0.17</x>
   <y>1</y>
   <z>-0.065</z>
  </axis>
 </animation>

 <animation>
  <type>rotate</type>
  <object-name>RAileron</object-name>
  <property>/surface-positions/right-aileron-pos-norm</property>
  <factor>-40</factor>
  <center>
   <x-m>0.24</x-m>
   <y-m>3.39</y-m>
   <z-m>0.04</z-m>
  </center>
  <axis>
   <x>0.17</x>
   <y>-1</y>
   <z>-0.065</z>
  </axis>
 </animation>

 <animation>
  <type>rotate</type>
  <object-name>CRAileron</object-name>
  <property>/surface-positions/right-aileron-pos-norm</property>
  <factor>-40</factor>
  <center>
   <x-m>0.24</x-m>
   <y-m>3.39</y-m>
   <z-m>0.04</z-m>
  </center>
  <axis>
   <x>0.17</x>
   <y>-1</y>
   <z>-0.065</z>
  </axis>
 </animation>

<!-- Flap bits -->
 <animation>
  <type>rotate</type>
  <object-name>LFlap</object-name>
  <property>/surface-positions/flap-pos-norm</property>
  <factor>70</factor>
  <center>
   <x-m>0.36</x-m>
   <y-m>-1.65</y-m>
   <z-m>-0.09</z-m>
  </center>
  <axis>
   <x>0.17</x>
   <y>1</y>
   <z>-0.065</z>
  </axis>
 </animation>

 <animation>
  <type>rotate</type>
  <object-name>CLFlap</object-name>
  <property>/surface-positions/flap-pos-norm</property>
  <factor>70</factor>
  <center>
   <x-m>0.36</x-m>
   <y-m>-1.65</y-m>
   <z-m>-0.09</z-m>
  </center>
  <axis>
   <x>0.17</x>
   <y>1</y>
   <z>-0.065</z>
  </axis>
 </animation>

 <animation>
  <type>rotate</type>
  <object-name>RFlap</object-name>
  <property>/surface-positions/flap-pos-norm</property>
  <factor>-70</factor>
  <center>
   <x-m>0.36</x-m>
   <y-m>1.65</y-m>
   <z-m>-0.09</z-m>
  </center>
  <axis>
   <x>0.17</x>
   <y>-1</y>
   <z>-0.065</z>
  </axis>
 </animation>

 <animation>
  <type>rotate</type>
  <object-name>CRFlap</object-name>
  <property>/surface-positions/flap-pos-norm</property>
  <factor>-70</factor>
  <center>
   <x-m>0.36</x-m>
   <y-m>1.65</y-m>
   <z-m>-0.09</z-m>
  </center>
  <axis>
   <x>0.17</x>
   <y>-1</y>
   <z>-0.065</z>
  </axis>
 </animation>

<!-- Landing Gear -->
<!-- Front u/c -->
 <animation>
  <type>rotate</type>
  <object-name>FStrut</object-name>
  <object-name>FTyre</object-name>
  <property>/gear/gear/position-norm</property>
  <offset-deg>120</offset-deg>
  <factor>-120</factor>
  <center>
   <x-m>-4.0</x-m>
   <y-m>0.0</y-m>
   <z-m>-0.4</z-m>
  </center>
  <axis>
   <x>0</x>
   <y>1</y>
   <z>0</z>
  </axis>
 </animation>

 <animation>
  <type>rotate</type>
  <object-name>CFStrut</object-name>
  <object-name>CFTyre</object-name>
  <property>/gear/gear/position-norm</property>
  <offset-deg>120</offset-deg>
  <factor>-120</factor>
  <center>
   <x-m>-4.0</x-m>
   <y-m>0.0</y-m>
   <z-m>-0.4</z-m>
  </center>
  <axis>
   <x>0</x>
   <y>1</y>
   <z>0</z>
  </axis>
 </animation>

 <animation>
  <type>rotate</type>
  <object-name>FDoor</object-name>
  <property>/gear/gear/position-norm</property>
  <offset-deg>-70</offset-deg>
  <factor>70</factor>
  <center>
   <x-m>-5.05</x-m>
   <y-m>0.0</y-m>
   <z-m>-0.07</z-m>
  </center>
  <axis>
   <x>0</x>
   <y>1</y>
   <z>0</z>
  </axis>
 </animation>

 <animation>
  <type>rotate</type>
  <object-name>CFDoor</object-name>
  <property>/gear/gear/position-norm</property>
  <offset-deg>-70</offset-deg>
  <factor>70</factor>
  <center>
   <x-m>-5.05</x-m>
   <y-m>0.0</y-m>
   <z-m>-0.07</z-m>
  </center>
  <axis>
   <x>0</x>
   <y>1</y>
   <z>0</z>
  </axis>
 </animation>

 <animation>
  <type>rotate</type>
  <object-name>BDoor</object-name>
  <property>/gear/gear/position-norm</property>
  <offset-deg>170</offset-deg>
  <factor>-170</factor>
  <center>
   <x-m>-4.0</x-m>
   <y-m>0.0</y-m>
   <z-m>-0.47</z-m>
  </center>
  <axis>
   <x>0</x>
   <y>1</y>
   <z>0</z>
  </axis>
 </animation>

 <animation>
  <type>rotate</type>
  <object-name>CBDoor</object-name>
  <property>/gear/gear/position-norm</property>
  <offset-deg>170</offset-deg>
  <factor>-170</factor>
  <center>
   <x-m>-4.0</x-m>
   <y-m>0.0</y-m>
   <z-m>-0.47</z-m>
  </center>
  <axis>
   <x>0</x>
   <y>1</y>
   <z>0</z>
  </axis>
 </animation>

<!-- Left u/c -->
 <animation>
  <type>rotate</type>
  <object-name>LStrut</object-name>
  <object-name>LTyre</object-name>
  <property>/gear/gear/position-norm</property>
  <offset-deg>100</offset-deg>
  <factor>-100</factor>
  <center>
   <x-m>0.08</x-m>
   <y-m>-1.45</y-m>
   <z-m>-0.13</z-m>
  </center>
  <axis>
   <x>1</x>
   <y>0</y>
   <z>0</z>
  </axis>
 </animation>

 <animation>
  <type>rotate</type>
  <object-name>CLStrut</object-name>
  <object-name>CLTyre</object-name>
  <property>/gear/gear/position-norm</property>
  <offset-deg>100</offset-deg>
  <factor>-100</factor>
  <center>
   <x-m>0.08</x-m>
   <y-m>-1.45</y-m>
   <z-m>-0.13</z-m>
  </center>
  <axis>
   <x>1</x>
   <y>0</y>
   <z>0</z>
  </axis>
 </animation>

 <animation>
  <type>rotate</type>
  <object-name>LDoor1</object-name>
  <object-name>LDoor2</object-name>
  <property>/gear/gear/position-norm</property>
  <offset-deg>85</offset-deg>
  <factor>-85</factor>
  <center>
   <x-m>0.08</x-m>
   <y-m>-1.58</y-m>
   <z-m>-0.14</z-m>
  </center>
  <axis>
   <x>1</x>
   <y>0</y>
   <z>0</z>
  </axis>
 </animation>

 <animation>
  <type>rotate</type>
  <object-name>CLDoor1</object-name>
  <object-name>CLDoor2</object-name>
  <property>/gear/gear/position-norm</property>
  <offset-deg>85</offset-deg>
  <factor>-85</factor>
  <center>
   <x-m>0.08</x-m>
   <y-m>-1.58</y-m>
   <z-m>-0.14</z-m>
  </center>
  <axis>
   <x>1</x>
   <y>0</y>
   <z>0</z>
  </axis>
 </animation>

<!-- Right u/c -->
 <animation>
  <type>rotate</type>
  <object-name>RStrut</object-name>
  <object-name>RTyre</object-name>
  <property>/gear/gear/position-norm</property>
  <offset-deg>-100</offset-deg>
  <factor>100</factor>
  <center>
   <x-m>0.08</x-m>
   <y-m>1.45</y-m>
   <z-m>-0.13</z-m>
  </center>
  <axis>
   <x>1</x>
   <y>0</y>
   <z>0</z>
  </axis>
 </animation>

 <animation>
  <type>rotate</type>
  <object-name>CRStrut</object-name>
  <object-name>CRTyre</object-name>
  <property>/gear/gear/position-norm</property>
  <offset-deg>-100</offset-deg>
  <factor>100</factor>
  <center>
   <x-m>0.08</x-m>
   <y-m>1.45</y-m>
   <z-m>-0.13</z-m>
  </center>
  <axis>
   <x>1</x>
   <y>0</y>
   <z>0</z>
  </axis>
 </animation>

 <animation>
  <type>rotate</type>
  <object-name>RDoor1</object-name>
  <object-name>RDoor2</object-name>
  <property>/gear/gear/position-norm</property>
  <offset-deg>-85</offset-deg>
  <factor>85</factor>
  <center>
   <x-m>0.08</x-m>
   <y-m>1.58</y-m>
   <z-m>-0.14</z-m>
  </center>
  <axis>
   <x>1</x>
   <y>0</y>
   <z>0</z>
  </axis>
 </animation>

 <animation>
  <type>rotate</type>
  <object-name>CRDoor1</object-name>
  <object-name>CRDoor2</object-name>
  <property>/gear/gear/position-norm</property>
  <offset-deg>-85</offset-deg>
  <factor>85</factor>
  <center>
   <x-m>0.08</x-m>
   <y-m>1.58</y-m>
   <z-m>-0.14</z-m>
  </center>
  <axis>
   <x>1</x>
   <y>0</y>
   <z>0</z>
  </axis>
 </animation>

</PropertyList>
